{
    "title": "Impact of Enhanced Soil Water Retention on Microbial Diversity in Arid Landscapes",
    "abstract": "Arid ecosystems are often limited by low water availability, which significantly impacts soil microbial diversity and function. This study investigates the causal relationship between the strategic improvement of water retention in desert soils and subsequent shifts in microbial community compositions. By integrating field experiments with advanced molecular biology techniques, we quantified changes in microbial diversity and abundance in soils where water retention was experimentally increased. Our results reveal that enhancing soil moisture retention leads to significant changes in the microbial community structure, including increases in microbial biomass, diversity, and shifts in community composition favoring moisture-dependent taxa. These findings suggest that modifications in soil physical properties can directly influence biological processes, which are critical for nutrient cycling and ecosystem sustainability in arid regions. The implications of this research are vital for developing sustainable agricultural practices and ecological restoration strategies in desert environments.",
    "entities": [
        "improved water retention in soils",
        "changes in desert soil microbial communities"
    ],
    "relationship_types": [
        "negatively correlate",
        "positively correlate",
        "cause",
        "inhibit"
    ],
    "relationships": [
        {
            "entity_1": "improved water retention in soils",
            "entity_2": "changes in desert soil microbial communities",
            "relationship": "cause"
        }
    ]
}